[
    {
        "user_name": "robotech83",
        "song": "Toxicity",
        "amount": 5,
        "priority": true,
        "cws_source": "dlc",
        "length_mins": 5.0
    },
    {
        "user_name": "robotech83",
        "song": "Toxicity",
        "amount": 5,
        "priority": true,
        "cws_source": "dlc",
        "length_mins": 5.0
    },
    {
        "user_name": "theidentitybooth",
        "song": "Knockin' on Heaven's Door",
        "amount": 1,
        "priority": false,
        "cws_source": "regular",
        "length_mins": 5.0
    },
    {
        "user_name": "theidentitybooth",
        "song": "Ultra Soul",
        "amount": 1,
        "priority": false,
        "cws_source": "regular",
        "length_mins": 5.0
    },
    {
        "user_name": "theidentitybooth",
        "song": "Peace of Mind",
        "amount": 1,
        "priority": false,
        "cws_source": "regular",
        "length_mins": 5.0
    },
    {
        "user_name": "theidentitybooth",
        "song": "Peace of Mind",
        "amount": 1,
        "priority": false,
        "cws_source": "regular",
        "length_mins": 5.0
    },
    {
        "user_name": "theidentitybooth",
        "song": "Knockin' on Heaven's Door",
        "amount": 4,
        "priority": false,
        "cws_source": "regular",
        "length_mins": 5.0
    }
]